oknpatch/__init__.py
oknpatch/gazefilters.json
oknpatch/okn_detection_rule.json
oknpatch/okndetector.gaze.config
oknpatch/oknpatch.py
oknpatch/oknserver_graph_plot_config.json
oknpatch/opm_detector_config.json
oknpatch-5.0.2.dist-info/LICENSE
oknpatch-5.0.2.dist-info/METADATA
oknpatch-5.0.2.dist-info/WHEEL
oknpatch-5.0.2.dist-info/entry_points.txt
oknpatch-5.0.2.dist-info/top_level.txt
oknpatch-5.0.2.dist-info/RECORD
